tests/__init__.py
tests/t.py
tests/t2.py
tests/test_blob_tracker.py
tests/test_mock_displayarray.py
tests/data/__init__.py
tests/mocks/__init__.py
tests/mocks/mock_displayarray.py
tests/test_util/__init__.py
tests/test_util/test_imu.py
virtualreality/__init__.py
virtualreality/__main__.py
virtualreality/main.py
virtualreality/calibration/__init__.py
virtualreality/calibration/camera_calibration.py
virtualreality/calibration/manual_color_mask_calibration.py
virtualreality/calibration/ai_tracker_training/__init__.py
virtualreality/calibration/ai_tracker_training/ai_tracker_training.py
virtualreality/calibration/ai_tracker_training/audio.py
virtualreality/calibration/ai_tracker_training/video.py
virtualreality/gui/__init__.py
virtualreality/gui/gui.py
virtualreality/logging/__init__.py
virtualreality/logging/log.py
virtualreality/server/__init__.py
virtualreality/server/__main__.py
virtualreality/server/server.py
virtualreality/templates/__init__.py
virtualreality/templates/poses.py
virtualreality/templates/template_base.py
virtualreality/templates/templates.py
virtualreality/templates/udu_templates.py
virtualreality/trackers/__init__.py
virtualreality/trackers/color_tracker.py
virtualreality/trackers/rgby_tracker.py
virtualreality/util/IMU.py
virtualreality/util/__init__.py
virtualreality/util/bluetooth.py
virtualreality/util/driver.py
virtualreality/util/kalman.py
virtualreality/util/utilz.py
virtualreality-0.1.2.dist-info/LICENSE
virtualreality-0.1.2.dist-info/METADATA
virtualreality-0.1.2.dist-info/WHEEL
virtualreality-0.1.2.dist-info/entry_points.txt
virtualreality-0.1.2.dist-info/top_level.txt
virtualreality-0.1.2.dist-info/RECORD
