Metadata-Version: 2.1
Name: virtualreality
Version: 0.1.2
Summary: python side of hobo_vr
Home-page: https://github.com/okawo80085/hobo_vr
Author: Okawo <okawo.198@gmail.com>, SimLeek <simulator.leek@gmail.com>
Author-email: 
License: UNKNOWN
Platform: UNKNOWN
Classifier: Development Status :: 2 - Pre-Alpha
Classifier: Intended Audience :: Developers
Classifier: Intended Audience :: Education
Classifier: Intended Audience :: End Users/Desktop
Classifier: Intended Audience :: Healthcare Industry
Classifier: Intended Audience :: Information Technology
Classifier: Intended Audience :: Manufacturing
Classifier: Intended Audience :: Science/Research
Classifier: Intended Audience :: Telecommunications Industry
Classifier: License :: OSI Approved :: MIT License
Classifier: Operating System :: OS Independent
Classifier: Programming Language :: C++
Classifier: Programming Language :: Python :: 3.7
Classifier: Topic :: Games/Entertainment
Classifier: Topic :: Multimedia :: Graphics :: Viewers
Classifier: Topic :: Scientific/Engineering :: Human Machine Interfaces
Classifier: Topic :: System :: Hardware :: Hardware Drivers
Requires-Python: >=3.7
Requires-Dist: aioconsole
Requires-Dist: docopt
Requires-Dist: numpy
Requires-Dist: pykalman
Requires-Dist: pyrr
Requires-Dist: pyserial
Requires-Dist: scipy
Provides-Extra: bluetooth
Requires-Dist: pybluez ; extra == 'bluetooth'
Provides-Extra: camera
Requires-Dist: displayarray ; extra == 'camera'
Requires-Dist: opencv-python ; extra == 'camera'
